zope.browserresource-5.1-py3.11-nspkg.pth
zope/browserresource/__init__.py
zope/browserresource/configure.zcml
zope/browserresource/directory.py
zope/browserresource/file.py
zope/browserresource/i18nfile.py
zope/browserresource/icon.py
zope/browserresource/interfaces.py
zope/browserresource/meta.zcml
zope/browserresource/metaconfigure.py
zope/browserresource/metadirectives.py
zope/browserresource/resource.py
zope/browserresource/resources.py
zope/browserresource/tests/__init__.py
zope/browserresource/tests/configure.txt
zope/browserresource/tests/support.py
zope/browserresource/tests/test_configure.py
zope/browserresource/tests/test_directives.py
zope/browserresource/tests/test_directory.py
zope/browserresource/tests/test_file.py
zope/browserresource/tests/test_i18nfile.py
zope/browserresource/tests/test_icondirective.py
zope/browserresource/tests/test_resource.py
zope/browserresource/tests/test_resources.py
zope/browserresource/tests/testfiles/test.gif
zope/browserresource/tests/testfiles/test.html
zope/browserresource/tests/testfiles/test.txt
zope/browserresource/tests/testfiles/test2.html
zope/browserresource/tests/testfiles/subdir/test.gif
zope.browserresource-5.1.dist-info/LICENSE.txt
zope.browserresource-5.1.dist-info/METADATA
zope.browserresource-5.1.dist-info/WHEEL
zope.browserresource-5.1.dist-info/namespace_packages.txt
zope.browserresource-5.1.dist-info/top_level.txt
zope.browserresource-5.1.dist-info/RECORD
